[{"id": "Unit1", "name": "Aguacate", "status": "OK", "moistLevel": 11200, "moistLimit": 10000, "waterTime": 1, "moistMeasureIntervall": 5, "logs": ["12.12.2023 12:00", "18.12.2023 12:00", "25.12.2023 12:00", "29.12.2023 12:00"], "sensor": "ADS.P0", "valve": 27}, {"id": "Unit2", "name": "Pepper", "status": "OK", "moistLevel": 11400, "moistLimit": 15000, "waterTime": 1, "moistMeasureIntervall": 10, "logs": ["12.12.2023 12:00", "18.12.2023 12:00", "25.12.2023 12:00", "29.12.2023 12:00"], "sensor": "ADS.P1", "valve": 22}, {"id": "Unit3", "name": "Dry plant", "status": "OK", "moistLevel": 17000, "moistLimit": 15000, "waterTime": 5, "moistMeasureIntervall": 10, "logs": ["12.12.2023 12:00", "18.12.2023 12:00", "25.12.2023 12:00", "29.12.2023 12:00"], "sensor": "ADS.P2", "valve": 10}, {"id": "Unit4", "name": "Avocado", "status": "OK", "moistLevel": 11400, "moistLimit": 12000, "waterTime": 5, "moistMeasureIntervall": 10, "logs": ["12.12.2023 12:00", "18.12.2023 12:00", "25.12.2023 12:00", "29.12.2023 12:00"], "sensor": "ADS.P3", "valve": 9}]